pympsym.cpython-39-x86_64-linux-gnu.so
pympsym-0.5.dist-info/WHEEL
pympsym-0.5.dist-info/RECORD
pympsym-0.5.dist-info/LICENSE.txt
pympsym-0.5.dist-info/top_level.txt
pympsym-0.5.dist-info/METADATA
