Metadata-Version: 2.1
Name: pympsym
Version: 0.5
Summary: MPSoC Symmetry Reduction
Home-page: https://github.com/Time0o/mpsym
Author: Timo Nicolai
Author-email: timonicolai@arcor.de
License: MIT
Platform: UNKNOWN
